<?xml version="1.0" encoding="utf-8" ?>
<dwsync>
<file name="settings.cpython-36.pyc" server="101.132.120.184/../var/www/html/" local="132698632550000000" remote="132698632550000000" Dst="0" />
<file name="wsgi.cpython-35.pyc" server="101.132.120.184/../var/www/html/" local="132698348800000000" remote="132698348800000000" Dst="0" />
<file name="__init__.cpython-36.pyc" server="101.132.120.184/../var/www/html/" local="132698451450000000" remote="132698451450000000" Dst="0" />
<file name="urls.cpython-36.pyc" server="101.132.120.184/../var/www/html/" local="132698451460000000" remote="132698451460000000" Dst="0" />
<file name="__init__.cpython-37.pyc" server="101.132.120.184/../var/www/html/" local="132698348800000000" remote="132698348800000000" Dst="0" />
<file name="urls.cpython-35.pyc" server="101.132.120.184/../var/www/html/" local="132698348800000000" remote="132698348800000000" Dst="0" />
<file name="wsgi.cpython-36.pyc" server="101.132.120.184/../var/www/html/" local="132698507040000000" remote="132698507040000000" Dst="0" />
<file name="__init__.cpython-35.pyc" server="101.132.120.184/../var/www/html/" local="132698639170000000" remote="132698639170000000" Dst="0" />
<file name="settings.cpython-35.pyc" server="101.132.120.184/../var/www/html/" local="132698348790000000" remote="132698348790000000" Dst="0" />
</dwsync>